ai12z/AiContextMeta.py
ai12z/AiENV.py
ai12z/AiProgressFail.py
ai12z/AiStatusCheck.py
ai12z/ConfigAi.py
ai12z/Context.py
ai12z/Data.py
ai12z/Doc.py
ai12z/Error.py
ai12z/Options.py
ai12z/QueryResponse.py
ai12z/Response.py
ai12z/Service.py
ai12z/Test.py
ai12z/__init__.py
ai12z_/AiContextMeta.py
ai12z_/AiENV.py
ai12z_/AiProgressFail.py
ai12z_/AiStatusCheck.py
ai12z_/ConfigAi.py
ai12z_/Context.py
ai12z_/Data.py
ai12z_/Doc.py
ai12z_/Error.py
ai12z_/Options.py
ai12z_/QueryResponse.py
ai12z_/Response.py
ai12z_/Service.py
ai12z_/Test.py
ai12z_/__init__.py
ai12z-1.1.0.dist-info/METADATA
ai12z-1.1.0.dist-info/WHEEL
ai12z-1.1.0.dist-info/top_level.txt
ai12z-1.1.0.dist-info/RECORD
