Metadata-Version: 2.1
Name: ai12z
Version: 1.1.0
